zapimoveis_scraper/__init__.py
zapimoveis_scraper/enums.py
zapimoveis_scraper/item.py
zapimoveis_scraper-0.4.0.data/scripts/zapimoveis
zapimoveis_scraper-0.4.0.dist-info/LICENSE
zapimoveis_scraper-0.4.0.dist-info/METADATA
zapimoveis_scraper-0.4.0.dist-info/WHEEL
zapimoveis_scraper-0.4.0.dist-info/top_level.txt
zapimoveis_scraper-0.4.0.dist-info/RECORD
