Metadata-Version: 2.1
Name: zapimoveis-scraper
Version: 0.4.0
Summary: zapimoveis-scraper is a Python package that works as a crawler and scraper using beautifulsoup4 to get data from zap imoveis
Home-page: https://github.com/GeovRodri/zapimoveis-scraper
Author: Geovany Rodrigues
Author-email: geovanyscv@gmail.com
License: UNKNOWN
Platform: UNKNOWN
Classifier: Development Status :: 5 - Production/Stable
Classifier: Intended Audience :: Developers
Classifier: License :: OSI Approved :: BSD License
Classifier: Environment :: Console
Classifier: Programming Language :: Python
Classifier: Topic :: Software Development :: Libraries :: Python Modules
Requires: beautifulsoup4
Provides: zapimoveis_scraper
License-File: LICENSE
Requires-Dist: beautifulsoup4
